spkpb/LICENSE.txt
spkpb/README.md
spkpb/__init__.py
spkpb/base.py
spkpb/problems.py
spkpb/speaker/__init__.py
spkpb/speaker/allinone.py
spkpb/speaker/log.py
spkpb/speaker/spk_interface.py
spkpb/speaker/term.py
spkpb/timer.py
spkpb-0.1.0b0.dist-info/WHEEL
spkpb-0.1.0b0.dist-info/METADATA
spkpb-0.1.0b0.dist-info/RECORD
