Metadata-Version: 2.1
Name: spkpb
Version: 0.1.0b0
Summary: A module to write programs which have to be verbose about a process on files and directories, and that have to emit informations, warnings and errors.
Home-page: https://github.com/projetmbc/tools-for-dev/tree/master/spkpb
License: GNU License Version 3
Author: Christophe BAL
Maintainer: Christophe BAL
Requires-Python: >=3.8,<4.0
Classifier: License :: Other/Proprietary License
Classifier: Programming Language :: Python :: 3
Classifier: Programming Language :: Python :: 3.8
Classifier: Programming Language :: Python :: 3.9
Requires-Dist: mistool (>=1.2.6-beta.0,<2.0.0)
Requires-Dist: natsort (>=7.1.1,<8.0.0)
Project-URL: Repository, https://github.com/projetmbc/tools-for-dev/tree/master/spkpb
